telfhash/VERSION
telfhash/__init__.py
telfhash/__main__.py
telfhash/grouping.py
telfhash/telfhash.py
telfhash-0.9.8.dist-info/LICENSE
telfhash-0.9.8.dist-info/METADATA
telfhash-0.9.8.dist-info/NOTICE
telfhash-0.9.8.dist-info/WHEEL
telfhash-0.9.8.dist-info/entry_points.txt
telfhash-0.9.8.dist-info/top_level.txt
telfhash-0.9.8.dist-info/RECORD
