Metadata-Version: 2.1
Name: telfhash
Version: 0.9.8
Summary: Generates hash for ELF files
Home-page: https://github.com/trendmicro/telfhash
Author: Fernando Merces, Joey Costoya
Author-email: UNKNOWN
License: Apache
Keywords: telfhash elf linux hash symbols
Platform: UNKNOWN
Classifier: Development Status :: 4 - Beta
Classifier: License :: OSI Approved :: Apache Software License
Classifier: Programming Language :: Python :: 3
Classifier: Programming Language :: Python :: 2.7
Requires-Dist: capstone (>=4.0.1)
Requires-Dist: nose (>=1.3.7)
Requires-Dist: packaging (>=20.9)
Requires-Dist: py-tlsh (>=4.5.0)
Requires-Dist: pyelftools (>=0.25)
Requires-Dist: python-tlsh (>=3.17.0)
